gradio_textboxplus/__init__.py
gradio_textboxplus/textboxplus.py
gradio_textboxplus/textboxplus.pyi
gradio_textboxplus/templates/component/Index-gzG44v87.js
gradio_textboxplus/templates/component/_basePickBy-CCYcMY6J.js
gradio_textboxplus/templates/component/_baseUniq-CJ22RRCW.js
gradio_textboxplus/templates/component/arc-C-TyVDlY.js
gradio_textboxplus/templates/component/architectureDiagram-KFL7JDKH-CXjvQNAM.js
gradio_textboxplus/templates/component/auto-render-BwaQGe8P.js
gradio_textboxplus/templates/component/blockDiagram-ZYB65J3Q-GnYr833V.js
gradio_textboxplus/templates/component/c4Diagram-AAMF2YG6-TZEZrq-6.js
gradio_textboxplus/templates/component/channel-_lhSgKsd.js
gradio_textboxplus/templates/component/chunk-ANTBXLJU-COyzUDjP.js
gradio_textboxplus/templates/component/chunk-FHKO5MBM-B9wH1RPo.js
gradio_textboxplus/templates/component/chunk-GLLZNHP4-SBuWW2Uc.js
gradio_textboxplus/templates/component/chunk-JBRWN2VN-BOrDDINV.js
gradio_textboxplus/templates/component/chunk-LXBSTHXV-63daW6bN.js
gradio_textboxplus/templates/component/chunk-NRVI72HA-p6eb86v0.js
gradio_textboxplus/templates/component/chunk-OMD6QJNC-1PWNBjDI.js
gradio_textboxplus/templates/component/chunk-WVR4S24B-C6QRPl_T.js
gradio_textboxplus/templates/component/classDiagram-3BZAVTQC-BOlhgpD6.js
gradio_textboxplus/templates/component/classDiagram-v2-QTMF73CY-BOlhgpD6.js
gradio_textboxplus/templates/component/clone-J26oJx2w.js
gradio_textboxplus/templates/component/cytoscape.esm-ZmItrg9y.js
gradio_textboxplus/templates/component/dagre-2BBEFEWP-ByH8KpRq.js
gradio_textboxplus/templates/component/defaultLocale-D7EN2tov.js
gradio_textboxplus/templates/component/diagram-4IRLE6MV-DDbNLQau.js
gradio_textboxplus/templates/component/diagram-GUPCWM2R-BJphRbjr.js
gradio_textboxplus/templates/component/diagram-RP2FKANI-CHP9iYpc.js
gradio_textboxplus/templates/component/erDiagram-HZWUO2LU-CFx8dvS9.js
gradio_textboxplus/templates/component/flowDiagram-THRYKUMA-BRxCnp1w.js
gradio_textboxplus-0.0.4.dist-info/METADATA
gradio_textboxplus-0.0.4.dist-info/WHEEL
gradio_textboxplus-0.0.4.dist-info/RECORD
